fluidgrids_cli/__init__.py
fluidgrids_cli/cli.py
fluidgrids_cli/config.py
fluidgrids_cli/utils.py
fluidgrids_cli/commands/__init__.py
fluidgrids_cli/commands/ai_commands.py
fluidgrids_cli/commands/auth_commands.py
fluidgrids_cli/commands/config_commands.py
fluidgrids_cli/commands/credential_commands.py
fluidgrids_cli/commands/dashboard_commands.py
fluidgrids_cli/commands/node_commands.py
fluidgrids_cli/commands/run_commands.py
fluidgrids_cli/commands/search_commands.py
fluidgrids_cli/commands/usage_commands.py
fluidgrids_cli/commands/workflow_commands.py
fluidgrids_cli-0.1.0.dist-info/licenses/LICENSE
fluidgrids_cli-0.1.0.dist-info/METADATA
fluidgrids_cli-0.1.0.dist-info/WHEEL
fluidgrids_cli-0.1.0.dist-info/entry_points.txt
fluidgrids_cli-0.1.0.dist-info/top_level.txt
fluidgrids_cli-0.1.0.dist-info/RECORD
