Metadata-Version: 2.4
Name: fluidgrids-cli
Version: 0.1.0
Summary: Command-line interface for the FluidGrids Workflow Engine
Home-page: https://fluidgrids.ai/
Author: Vignesh T.V
Author-email: vignesh@algoshred.com
Classifier: Development Status :: 4 - Beta
Classifier: Intended Audience :: Developers
Classifier: License :: OSI Approved :: MIT License
Classifier: Operating System :: OS Independent
Classifier: Programming Language :: Python :: 3
Classifier: Programming Language :: Python :: 3.8
Classifier: Programming Language :: Python :: 3.9
Classifier: Programming Language :: Python :: 3.10
Classifier: Programming Language :: Python :: 3.11
Requires-Python: >=3.8
License-File: LICENSE
Requires-Dist: fluidgrids==0.1.0
Requires-Dist: click>=8.0.0
Requires-Dist: pyyaml>=6.0
Requires-Dist: rich>=12.0.0
Requires-Dist: keyring>=23.0.0
Requires-Dist: tabulate>=0.8.0
Dynamic: author
Dynamic: author-email
Dynamic: classifier
Dynamic: description
Dynamic: description-content-type
Dynamic: home-page
Dynamic: license-file
Dynamic: requires-dist
Dynamic: requires-python
Dynamic: summary
